[{"id":"1","location_id":"1","number":"'+1 801-581-2000","extension":"None","type":"Office","language":"EN","description":"description"},{"id":"2","location_id":"2","number":"'+1 801-213-4500","extension":"None","type":"Office","language":"EN","description":"Primary number pulled from Google Maps listing."},{"id":"3","location_id":"3","number":"'+1 801-213-3200","extension":"None","type":"Office","language":"EN","description":"Primary number pulled from Google Maps listing."},{"id":"4","location_id":"4","number":"'+1 801-213-9900","extension":"None","type":"Office","language":"EN","description":"Primary number pulled from Google Maps listing."},{"id":"5","location_id":"5","number":"'+1 435-658-9200","extension":"None","type":"Office","language":"EN","description":"Primary number pulled from Google Maps listing."},{"id":"6","location_id":"6","number":"'+1 801-501-2100","extension":"None","type":"Office","language":"EN","description":"Primary number pulled from Google Maps listing."},{"id":"7","location_id":"7","number":"'+1 435-207-4800","extension":"None","type":"Office","language":"EN","description":"Primary number pulled from Google Maps listing."},{"id":"8","location_id":"8","number":"'+1 435-865-3440","extension":"None","type":"Office","language":"EN","description":"Primary number pulled from Google Maps listing."},{"id":"9","location_id":"9","number":"'+1 801-314-7777","extension":"None","type":"Office","language":"EN","description":"Primary number pulled from Google Maps listing."},{"id":"10","location_id":"10","number":"'+1 435-283-4076","extension":"None","type":"Office","language":"EN","description":"Primary number pulled from Google Maps listing."},{"id":"11","location_id":"11","number":"'+1 435-743-5555","extension":"None","type":"Office","language":"EN","description":"Primary number pulled from Google Maps listing."},{"id":"12","location_id":"12","number":"'+1 435-676-8811","extension":"None","type":"Office","language":"EN","description":"Primary number pulled from Google Maps listing."},{"id":"13","location_id":"13","number":"'+1 435-657-4500","extension":"None","type":"Office","language":"EN","description":"Primary number pulled from Google Maps listing."},{"id":"14","location_id":"14","number":"'+1  801-779-6200","extension":"None","type":"Office","language":"EN","description":"Primary number pulled from Google Maps listing."},{"id":"15","location_id":"15","number":"'+1 801-753-4310","extension":"None","type":"Office","language":"EN","description":"Primary number pulled from Google Maps listing."},{"id":"16","location_id":"16","number":"'+1 435-563-4888","extension":"None","type":"Office","language":"EN","description":"Primary number pulled from Google Maps listing."},{"id":"17","location_id":"17","number":"'+1 801-786-7500","extension":"None","type":"Office","language":"EN","description":"Primary number pulled from Google Maps listing."},{"id":"18","location_id":"18","number":"'+1 435-615-5707","extension":"None","type":"Office","language":"EN","description":"Primary number pulled from Google Maps listing."},{"id":"19","location_id":"19","number":"'+1 435-688-6000","extension":"None","type":"Office","language":"EN","description":"Primary number pulled from Google Maps listing."},{"id":"20","location_id":"20","number":"'+1 385-282-2000","extension":"None","type":"Office","language":"EN","description":"Primary number pulled from Google Maps listing."},{"id":"21","location_id":"21","number":"'+1 435-893-0580","extension":"None","type":"Office","language":"EN","description":"Primary number pulled from Google Maps listing."},{"id":"22","location_id":"22","number":"'+1 801-285-4000","extension":"None","type":"Office","language":"EN","description":"Primary number pulled from Google Maps listing."},{"id":"23","location_id":"23","number":"'+1 801-429-1250","extension":"None","type":"Office","language":"EN","description":"Primary number pulled from Google Maps listing."},{"id":"24","location_id":"24","number":"'+1 801-840-2000","extension":"None","type":"Office","language":"EN","description":"Primary number pulled from Google Maps listing."},{"id":"25","location_id":"25","number":"'+1 435-228-1200","extension":"None","type":"Office","language":"EN","description":"Primary number pulled from Google Maps listing."}]